AUTHORS
CHANGELOG.rst
CONTRIBUTING.rst
LICENSE
LICENSE.flashmedia
LICENSE.pbs
MANIFEST.in
README.rst
requirements-docs.txt
setup.py
docs/Makefile
docs/api.rst
docs/changelog.rst
docs/cli.rst
docs/conf.py
docs/index.rst
docs/install.rst
docs/issues.rst
docs/plugin_matrix.rst
docs/twitch_oauth.rst
docs/_static/flattr-badge.png
docs/_themes/.gitignore
docs/_themes/LICENSE
docs/_themes/flask_theme_support.py
docs/_themes/cr_small/layout.html
docs/_themes/cr_small/theme.conf
docs/_themes/cr_small/static/flasky.css_t
examples/gst-player.py
src/livestreamer/__init__.py
src/livestreamer/buffers.py
src/livestreamer/cache.py
src/livestreamer/compat.py
src/livestreamer/exceptions.py
src/livestreamer/logger.py
src/livestreamer/options.py
src/livestreamer/session.py
src/livestreamer/utils.py
src/livestreamer.egg-info/PKG-INFO
src/livestreamer.egg-info/SOURCES.txt
src/livestreamer.egg-info/dependency_links.txt
src/livestreamer.egg-info/entry_points.txt
src/livestreamer.egg-info/requires.txt
src/livestreamer.egg-info/top_level.txt
src/livestreamer/packages/__init__.py
src/livestreamer/packages/pbs.py
src/livestreamer/packages/flashmedia/__init__.py
src/livestreamer/packages/flashmedia/amf.py
src/livestreamer/packages/flashmedia/box.py
src/livestreamer/packages/flashmedia/compat.py
src/livestreamer/packages/flashmedia/error.py
src/livestreamer/packages/flashmedia/f4v.py
src/livestreamer/packages/flashmedia/flv.py
src/livestreamer/packages/flashmedia/ordereddict.py
src/livestreamer/packages/flashmedia/packet.py
src/livestreamer/packages/flashmedia/tag.py
src/livestreamer/packages/flashmedia/types.py
src/livestreamer/packages/flashmedia/util.py
src/livestreamer/plugin/__init__.py
src/livestreamer/plugin/plugin.py
src/livestreamer/plugin/api/__init__.py
src/livestreamer/plugin/api/http_session.py
src/livestreamer/plugins/__init__.py
src/livestreamer/plugins/afreecatv.py
src/livestreamer/plugins/alieztv.py
src/livestreamer/plugins/azubutv.py
src/livestreamer/plugins/bambuser.py
src/livestreamer/plugins/beattv.py
src/livestreamer/plugins/cast3d.py
src/livestreamer/plugins/chaturbate.py
src/livestreamer/plugins/common_swf.py
src/livestreamer/plugins/crunchyroll.py
src/livestreamer/plugins/cybergame.py
